odoo/addons/pos_report_discount/README.rst
odoo/addons/pos_report_discount/__init__.py
odoo/addons/pos_report_discount/__manifest__.py
odoo/addons/pos_report_discount/i18n/es.po
odoo/addons/pos_report_discount/i18n/fr.po
odoo/addons/pos_report_discount/i18n/it.po
odoo/addons/pos_report_discount/i18n/pos_report_discount.pot
odoo/addons/pos_report_discount/models/__init__.py
odoo/addons/pos_report_discount/models/report_pos_order.py
odoo/addons/pos_report_discount/readme/CONTRIBUTORS.rst
odoo/addons/pos_report_discount/readme/DESCRIPTION.rst
odoo/addons/pos_report_discount/static/description/icon.png
odoo/addons/pos_report_discount/static/description/index.html
odoo/addons/pos_report_discount/tests/__init__.py
odoo/addons/pos_report_discount/tests/test_report_pos_order.py
odoo/addons/pos_report_discount/views/report_pos_order.xml
odoo14_addon_pos_report_discount-14.0.1.0.1.dev10.dist-info/METADATA
odoo14_addon_pos_report_discount-14.0.1.0.1.dev10.dist-info/WHEEL
odoo14_addon_pos_report_discount-14.0.1.0.1.dev10.dist-info/top_level.txt
odoo14_addon_pos_report_discount-14.0.1.0.1.dev10.dist-info/RECORD
